<?xml version="1.0" encoding="utf-8" ?>
<dwsync>
<file name="header_bg.gif" server="arev.p.ht" local="130211557871562500" remote="130212388200000000" />
<file name="but.gif" server="arev.p.ht" local="130211557884687500" remote="130212388200000000" />
<file name="bg.gif" server="arev.p.ht" local="130211557918437500" remote="130212388200000000" />
<file name="footer_bg.gif" server="arev.p.ht" local="130211557875625000" remote="130212388200000000" />
<file name="item_bg.gif" server="arev.p.ht" local="130211557855781250" remote="130212388200000000" />
<file name="item_bg_new.gif" server="arev.p.ht" local="130211557851406250" remote="130212388200000000" />
<file name="view_bg.gif" server="arev.p.ht" local="130211557826406250" remote="130212388200000000" />
<file name="buy_bg.gif" server="arev.p.ht" local="130211557881250000" remote="130212388200000000" />
<file name="telephone.jpg" server="arev.p.ht" local="130211557833593750" remote="130212388200000000" />
<file name="header.jpg" server="arev.p.ht" local="130211557877343750" remote="130212388800000000" />
</dwsync>